{
  "type": "FeatureCollection",
  "features": [
    {
      "type": "Feature",
      "geometry": {
        "type": "Point",
        "coordinates": [
          -6.309119,
          53.346295
        ]
      },
      "properties": {
        "marker-symbol": "pitch",
        "name": "Liffey Valley AC",
        "address": "Sand Pitts Cottage, Islandbridge",
        "popupContent": "Liffey Valley AC"
      }
    }
  ]
}
