{
  "type": "FeatureCollection",
  "features": [
    {
      "type": "Feature",
      "geometry": {
        "type": "Point",
        "coordinates": [
          53.346295,
          -6.309119
        ]
      },
      "properties": {
        "marker-symbol": "pitch",
        "name": "Liffey Valley AC",
        "address": "Sand Pitts Cottage, Islandbridge"
      }
    }
  ]
}
